iceDP/__init__.py
iceDP/filterling.py
iceDP/main_procedure.py
iceDP/plot_spots.py
iceDP/setup.py
iceDP-1.0.0.dist-info/METADATA
iceDP-1.0.0.dist-info/WHEEL
iceDP-1.0.0.dist-info/top_level.txt
iceDP-1.0.0.dist-info/RECORD
