Metadata-Version: 2.1
Name: iceDP
Version: 1.0.0
Summary: Identify inter-chromatin interaction utilize density peaks algorithm
Home-page: https://github.com/JiekaiLab/iceDP
Author: RH Chen
Author-email: 695518083@qq.com
License: MIT
Platform: UNKNOWN
Classifier: License :: OSI Approved :: MIT License
Classifier: Programming Language :: Python :: 3
Classifier: Programming Language :: Python :: 3.7
Requires-Dist: pandas
Requires-Dist: numpy
Requires-Dist: math
Requires-Dist: multiprocessing
Requires-Dist: functools
Requires-Dist: scipy
